fastopenapi/__init__.py
fastopenapi/base_router.py
fastopenapi/error_handler.py
fastopenapi/routers/__init__.py
fastopenapi/routers/aiohttp.py
fastopenapi/routers/falcon.py
fastopenapi/routers/flask.py
fastopenapi/routers/quart.py
fastopenapi/routers/sanic.py
fastopenapi/routers/starlette.py
fastopenapi/routers/tornado.py
fastopenapi-0.7.0.dist-info/LICENSE
fastopenapi-0.7.0.dist-info/METADATA
fastopenapi-0.7.0.dist-info/WHEEL
fastopenapi-0.7.0.dist-info/RECORD
