Metadata-Version: 2.3
Name: fastopenapi
Version: 0.7.0
Summary: FastOpenAPI is a library for generating and integrating OpenAPI schemas using Pydantic v2 and various frameworks (AioHttp, Falcon, Flask, Quart, Sanic, Starlette, Tornado).
License: MIT
Author: Nikita Ryzhenkov
Author-email: nikita.ryzhenkoff@gmail.com
Requires-Python: >=3.10
Classifier: Development Status :: 4 - Beta
Classifier: Environment :: Web Environment
Classifier: Framework :: Pydantic :: 2
Classifier: Intended Audience :: Developers
Classifier: Intended Audience :: Information Technology
Classifier: License :: OSI Approved :: MIT License
Classifier: Operating System :: OS Independent
Classifier: Programming Language :: Python
Classifier: Programming Language :: Python :: 3
Classifier: Programming Language :: Python :: 3 :: Only
Classifier: Programming Language :: Python :: 3.10
Classifier: Programming Language :: Python :: 3.11
Classifier: Programming Language :: Python :: 3.12
Classifier: Programming Language :: Python :: 3.13
Classifier: Topic :: Internet
Classifier: Topic :: Software Development
Classifier: Topic :: Software Development :: Libraries
Classifier: Topic :: Software Development :: Libraries :: Python Modules
Provides-Extra: aiohttp
Provides-Extra: falcon
Provides-Extra: flask
Provides-Extra: quart
Provides-Extra: sanic
Provides-Extra: starlette
Provides-Extra: tornado
Requires-Dist: aiohttp (>=3.11.0,<3.12.0) ; extra == "aiohttp"
Requires-Dist: falcon (>=4.0.2,<5.0.0) ; extra == "falcon"
Requires-Dist: flask (>=3.1.0,<4.0.0) ; extra == "flask"
Requires-Dist: pydantic (>=2.10.6,<3.0.0)
Requires-Dist: quart (>=0.20.0,<0.21.0) ; extra == "quart"
Requires-Dist: sanic (>=24.12.0,<25.0.0) ; extra == "sanic"
Requires-Dist: starlette (>=0.46.0,<0.47.0) ; extra == "starlette"
Requires-Dist: tornado (>=6.4.0,<6.5.0) ; extra == "tornado"
Project-URL: Documentation, https://fastopenapi.fatalyst.dev/
Project-URL: Homepage, https://fastopenapi.fatalyst.dev/
Project-URL: Issues, https://github.com/mr-fatalyst/fastopenapi/issues
Project-URL: Repository, https://github.com/mr-fatalyst/fastopenapi
